fast_ticc/LICENSE
fast_ticc/README.md
fast_ticc/__init__.py
fast_ticc/admm/__init__.py
fast_ticc/admm/front_end.py
fast_ticc/admm/solver.py
fast_ticc/admm/unique_values.py
fast_ticc/cluster_label_assignment.py
fast_ticc/cluster_maintenance.py
fast_ticc/cluster_metrics.py
fast_ticc/containers/__init__.py
fast_ticc/containers/arguments.py
fast_ticc/containers/model_state.py
fast_ticc/containers/results.py
fast_ticc/data_preparation.py
fast_ticc/example_data.txt
fast_ticc/front_end.py
fast_ticc/graphical_lasso.py
fast_ticc/likelihood.py
fast_ticc/main_loop.py
fast_ticc/matrix_compression.py
fast_ticc/numba_guard.py
fast_ticc/ticc_types.py
fast_ticc-1.0.1.dist-info/LICENSE
fast_ticc-1.0.1.dist-info/METADATA
fast_ticc-1.0.1.dist-info/WHEEL
fast_ticc-1.0.1.dist-info/RECORD
