Metadata-Version: 2.1
Name: fast-ticc
Version: 1.0.1
Summary: Covariance-based clustering of multivariate time-series data.
Home-page: https://github.com/sandialabs/fast_ticc
License: BSD-3-Clause
Keywords: clustering,inverse covariance,ticc,multivariate data,time series data,toeplitz
Author: Andy Wilson
Author-email: atwilso@sandia.gov
Maintainer: Andy Wilson
Maintainer-email: atwilso@sandia.gov
Requires-Python: >=3.6
Classifier: Development Status :: 5 - Production/Stable
Classifier: Intended Audience :: Science/Research
Classifier: License :: OSI Approved :: BSD License
Classifier: Programming Language :: Python :: 3
Classifier: Programming Language :: Python :: 3.6
Classifier: Programming Language :: Python :: 3.7
Classifier: Programming Language :: Python :: 3.8
Classifier: Programming Language :: Python :: 3.9
Classifier: Programming Language :: Python :: 3.10
Classifier: Programming Language :: Python :: 3.11
Classifier: Programming Language :: Python :: 3
Classifier: Topic :: Scientific/Engineering :: Information Analysis
Requires-Dist: numba (>=0.53.0)
Requires-Dist: numpy (>=1.22)
Requires-Dist: scikit-learn (>=1.0.0)
Project-URL: Documentation, https://fast-ticc.readthedocs.io
Project-URL: Repository, https://github.com/sandialabs/fast_ticc
